examples/__init__.py
examples/bb84_example.py
quantum_attack_simulator/__init__.py
quantum_attack_simulator/communication.py
quantum_attack_simulator/bb84/__init__.py
quantum_attack_simulator/bb84/attacker.py
quantum_attack_simulator/bb84/receiver.py
quantum_attack_simulator/bb84/sender.py
quantum_attack_simulator/bb84/visualization.py
quantum_attack_simulator-1.0.2.dist-info/licenses/LICENSE
quantum_attack_simulator-1.0.2.dist-info/METADATA
quantum_attack_simulator-1.0.2.dist-info/WHEEL
quantum_attack_simulator-1.0.2.dist-info/entry_points.txt
quantum_attack_simulator-1.0.2.dist-info/top_level.txt
quantum_attack_simulator-1.0.2.dist-info/RECORD
