Metadata-Version: 2.4
Name: quantum-attack-simulator
Version: 1.0.2
Summary: A Python library for simulating BB84 protocol security and attacks.
Home-page: https://github.com/koraydns/quantum-attack-simulator
Author: Koray Danisma
Author-email: koray.danisma@gmail.com
Project-URL: Source, https://github.com/koraydns/quantum-attack-simulator
Project-URL: Paper, https://doi.org/10.5281/zenodo.17586868
Project-URL: Documentation, https://github.com/koraydns/quantum-attack-simulator#readme
Classifier: Programming Language :: Python :: 3
Classifier: License :: OSI Approved :: Apache Software License
Classifier: Operating System :: OS Independent
Classifier: Development Status :: 4 - Beta
Classifier: Intended Audience :: Science/Research
Classifier: Intended Audience :: Education
Classifier: Topic :: Scientific/Engineering :: Physics
Classifier: Topic :: Security
Classifier: Topic :: Security :: Cryptography
Classifier: Natural Language :: English
Requires-Python: >=3.7
License-File: LICENSE
Requires-Dist: qiskit>=0.45.0
Requires-Dist: qiskit-aer>=0.13.1
Requires-Dist: matplotlib>=3.8.2
Dynamic: author
Dynamic: author-email
Dynamic: classifier
Dynamic: description
Dynamic: description-content-type
Dynamic: home-page
Dynamic: license-file
Dynamic: project-url
Dynamic: requires-dist
Dynamic: requires-python
Dynamic: summary
